google_analytics_driver/__init__.py
google_analytics_driver/clients.py
google_analytics_driver/logic.py
google_analytics_driver/resolve.py
google_analytics_driver/retrieve.py
google_analytics_driver/service.py
hirmeos_google_analytics_driver-0.1.1.dist-info/LICENSE
hirmeos_google_analytics_driver-0.1.1.dist-info/METADATA
hirmeos_google_analytics_driver-0.1.1.dist-info/WHEEL
hirmeos_google_analytics_driver-0.1.1.dist-info/top_level.txt
hirmeos_google_analytics_driver-0.1.1.dist-info/RECORD
