Metadata-Version: 2.1
Name: hirmeos-google-analytics-driver
Version: 0.1.1
Summary: Functions required by the google-analytics-local-driver
Author-email: Tai Jantarungsee <tai.jantarungsee@ubiquitypress.com>
Project-URL: Homepage, https://gitlab.com/ubiquitypress/google_analytics_driver
Classifier: Programming Language :: Python :: 3
Classifier: License :: OSI Approved :: MIT License
Classifier: Operating System :: OS Independent
Requires-Python: >=3.10
License-File: LICENSE
Requires-Dist: hirmeos-clients (>=0.1.6)
Requires-Dist: flake8 (==3.6.0)
Requires-Dist: google-api-core (==1.14.3)
Requires-Dist: google-api-python-client (==1.7.11)
Requires-Dist: google-auth (==1.6.3)
